[
	{
		"ID": "411",
		"question": "The ambulance whose year of registration is 2002, had the first mandatory periodic inspection in:",
		"image": "https://raw.githubusercontent.com/sdriveportugal/web/refs/heads/main/SetPics/circulation-1/411.png",
		"optionA": "2003",
		"optionB": "2004",
		"optionC": "2006",
		"Answer": "A",
		"Explanation": "For Explanation, please be a member or comment on our youtube channel."
	},
	{
		"ID": "414",
		"question": "Should the ambulance give way when entering the motorway?",
		"image": "https://raw.githubusercontent.com/sdriveportugal/web/refs/heads/main/SetPics/circulation-1/414.png",
		"optionA": "No.",
		"optionB": "Yes.",
		"optionC": "",
		"Answer": "B",
		"Explanation": "For Explanation, please be a member or comment on our youtube channel."
	},
	{
		"ID": "415",
		"question": "Should the ambulance stop at the Stop sign?",
		"image": "https://raw.githubusercontent.com/sdriveportugal/web/refs/heads/main/SetPics/circulation-1/415.png",
		"optionA": "No, because it signals a rescue march",
		"optionB": "No, because it's a vehicle built for emergency missions..",
		"optionC": "Yes, always",
		"Answer": "C",
		"Explanation": "For Explanation, please be a member or comment on our youtube channel."
	},
	{
		"ID": "423",
		"question": "Idling that causes unjustified embarrassment to road users is punishable by the Highway Code.",
		"image": "https://raw.githubusercontent.com/sdriveportugal/web/refs/heads/main/SetPics/circulation-1/423.png",
		"optionA": "The statement is false",
		"optionB": "The statement is true",
		"optionC": "",
		"Answer": "B",
		"Explanation": "For Explanation, please be a member or comment on our youtube channel."
	},
	{
		"ID": "424",
		"question": "Circulation on the 25 de Abril Bridge is prohibited to the following categories of vehicles:",
		"image": "https://raw.githubusercontent.com/sdriveportugal/web/refs/heads/main/SetPics/circulation-1/424.png",
		"optionA": "Articulated vehicle combinations",
		"optionB": "Motorbikes up to 50 cc",
		"optionC": "All motorbikes",
		"Answer": "B",
		"Explanation": "For Explanation, please be a member or comment on our youtube channel."
	},
	{
		"ID": "428",
		"question": "The decision I take in each situation:",
		"image": "https://raw.githubusercontent.com/sdriveportugal/web/refs/heads/main/SetPics/circulation-1/428.png",
		"optionA": "It depends exclusively on the signposts I see",
		"optionB": "This is only due to the intensity of the traffic",
		"optionC": "It's always influenced by the forecast I make",
		"Answer": "C",
		"Explanation": "For Explanation, please be a member or comment on our youtube channel."
	},
	{
		"ID": "432",
		"question": "The minimum distance to be kept from the vehicle in front of me:",
		"image": "https://raw.githubusercontent.com/sdriveportugal/web/refs/heads/main/SetPics/circulation-1/432.png",
		"optionA": "It must be the one that allows me, if necessary, to safely immobilise the vehicle",
		"optionB": "Must not be less than 30 metres",
		"optionC": "No longer than the stopping distance",
		"Answer": "A",
		"Explanation": "For Explanation, please be a member or comment on our youtube channel."
	},
	{
		"ID": "434",
		"question": "The carriageway, in which it circles, has:",
		"image": "https://raw.githubusercontent.com/sdriveportugal/web/refs/heads/main/SetPics/circulation-1/434.png",
		"optionA": "Two-way",
		"optionB": "Two lanes in each direction",
		"optionC": "Three lanes of traffic in the same direction",
		"Answer": "C",
		"Explanation": "For Explanation, please be a member or comment on our youtube channel."
	},
	{
		"ID": "448",
		"question": "Driving safety depends on each driver's constant assessment of risk.",
		"image": "https://raw.githubusercontent.com/sdriveportugal/web/refs/heads/main/SetPics/circulation-1/448.png",
		"optionA": "Right",
		"optionB": "Wrong",
		"optionC": "",
		"Answer": "A",
		"Explanation": "For Explanation, please be a member or comment on our youtube channel."
	},
	{
		"ID": "451",
		"question": "The signage on this public road allows me to use the sidewalks. Do you agree with this statement?",
		"image": "https://raw.githubusercontent.com/sdriveportugal/web/refs/heads/main/SetPics/circulation-1/451.png",
		"optionA": "No, use of the sidewalk is prohibited",
		"optionB": "Yes, but only the sidewalk on the right-hand side of the road",
		"optionC": "Yes, the sidewalk is wide enough and the signage does not prohibit it..",
		"Answer": "A",
		"Explanation": "For Explanation, please be a member or comment on our youtube channel."
	},
	{
		"ID": "459",
		"question": "When crossing the carriageway, should pedestrians make sure that they can do so without danger of accident?",
		"image": "https://raw.githubusercontent.com/sdriveportugal/web/refs/heads/main/SetPics/circulation-1/459.png",
		"optionA": "No, unless they cross the carriageway outside a pedestrian crossing",
		"optionB": "No.",
		"optionC": "Yes, at all times",
		"Answer": "C",
		"Explanation": "For Explanation, please be a member or comment on our youtube channel."
	},
	{
		"ID": "462",
		"question": "When driving on this acceleration lane, do I have the right of way over vehicles on the public road I am going to enter?",
		"image": "https://raw.githubusercontent.com/sdriveportugal/web/refs/heads/main/SetPics/circulation-1/462.png",
		"optionA": "No, never",
		"optionB": "Yes, because I'm on the right",
		"optionC": "Yes.",
		"Answer": "A",
		"Explanation": "For Explanation, please be a member or comment on our youtube channel."
	},
	{
		"ID": "467",
		"question": "When driving in this location, a driver should know that:",
		"image": "https://raw.githubusercontent.com/sdriveportugal/web/refs/heads/main/SetPics/circulation-1/467.png",
		"optionA": "You are travelling within a locality because it is an area with buildings",
		"optionB": "Driving on a road reserved for cars and motorbikes only",
		"optionC": "",
		"Answer": "A",
		"Explanation": "For Explanation, please be a member or comment on our youtube channel."
	},
	{
		"ID": "468",
		"question": "When driving on a motorway, I am obliged to give way to the ambulance that enters it.",
		"image": "https://raw.githubusercontent.com/sdriveportugal/web/refs/heads/main/SetPics/circulation-1/468.png",
		"optionA": "Right",
		"optionB": "Wrong",
		"optionC": "",
		"Answer": "B",
		"Explanation": "For Explanation, please be a member or comment on our youtube channel."
	},
	{
		"ID": "480",
		"question": "The rotating blue lights on the top of a vehicle indicate:",
		"image": "https://raw.githubusercontent.com/sdriveportugal/web/refs/heads/main/SetPics/circulation-1/480.png",
		"optionA": "The presence and movement of a slow-moving vehicle",
		"optionB": "That the vehicle is travelling on an urgent rescue mission",
		"optionC": "The vehicle is carrying dangerous materials",
		"Answer": "B",
		"Explanation": "For Explanation, please be a member or comment on our youtube channel."
	},
	{
		"ID": "482",
		"question": "Should hazard lights be used whenever there is a need to reduce speed suddenly?",
		"image": "https://raw.githubusercontent.com/sdriveportugal/web/refs/heads/main/SetPics/circulation-1/482.png",
		"optionA": "No, they should only be used in the event of an accident",
		"optionB": "No, they should only be used if the vehicle breaks down on the public highway or in the event of an accident",
		"optionC": "Yes, whenever there is a danger to other road users",
		"Answer": "C",
		"Explanation": "For Explanation, please be a member or comment on our youtube channel."
	},
	{
		"ID": "487",
		"question": "Do the rules of the Highway Code apply to all roads in the public domain?",
		"image": "https://raw.githubusercontent.com/sdriveportugal/web/refs/heads/main/SetPics/circulation-1/487.png",
		"optionA": "No.",
		"optionB": "Yes.",
		"optionC": "",
		"Answer": "B",
		"Explanation": "For Explanation, please be a member or comment on our youtube channel."
	},
	{
		"ID": "488",
		"question": "Can the rules of the Highway Code also apply on roads in the private domain?",
		"image": "https://raw.githubusercontent.com/sdriveportugal/web/refs/heads/main/SetPics/circulation-1/488.png",
		"optionA": "No, even if open to public traffic",
		"optionB": "Yes, when open to public traffic",
		"optionC": "",
		"Answer": "B",
		"Explanation": "For Explanation, please be a member or comment on our youtube channel."
	},
	{
		"ID": "490",
		"question": "If you are involved in a road accident, you must identify yourself:",
		"image": "https://raw.githubusercontent.com/sdriveportugal/web/refs/heads/main/SetPics/circulation-1/490.png",
		"optionA": "To those involved in the accident and the authorities",
		"optionB": "Only if there are injuries",
		"optionC": "Only to the police officer",
		"Answer": "A",
		"Explanation": "For Explanation, please be a member or comment on our youtube channel."
	},
	{
		"ID": "491",
		"question": "I give the passage to the ambulance because:",
		"image": "https://raw.githubusercontent.com/sdriveportugal/web/refs/heads/main/SetPics/circulation-1/491.png",
		"optionA": "Mark the emergency gear appropriately",
		"optionB": "It is always a priority vehicle",
		"optionC": "Leaving a car park and turning right",
		"Answer": "A",
		"Explanation": "For Explanation, please be a member or comment on our youtube channel."
	},
	{
		"ID": "493",
		"question": "Do I drive correctly in the left lane?",
		"image": "https://raw.githubusercontent.com/sdriveportugal/web/refs/heads/main/SetPics/circulation-1/493.png",
		"optionA": "Yes, because I can always drive in the left-hand lane",
		"optionB": "Yes, because I'm going straight ahead and overtaking",
		"optionC": "",
		"Answer": "B",
		"Explanation": "For Explanation, please be a member or comment on our youtube channel."
	},
	{
		"ID": "495",
		"question": "Do I drive properly on this traffic lane?",
		"image": "https://raw.githubusercontent.com/sdriveportugal/web/refs/heads/main/SetPics/circulation-1/495.png",
		"optionA": "No, because within a town I must use the traffic lane furthest to the left",
		"optionB": "Yes, because I always have to take the rightmost traffic lane within the town",
		"optionC": "Yes, if I'm going straight ahead",
		"Answer": "C",
		"Explanation": "For Explanation, please be a member or comment on our youtube channel."
	},
	{
		"ID": "503",
		"question": "I circulate in a locality. Can I use this traffic lane?",
		"image": "https://raw.githubusercontent.com/sdriveportugal/web/refs/heads/main/SetPics/circulation-1/503.png",
		"optionA": "No, I'm obliged to use the traffic queue furthest to the right",
		"optionB": "Yes, because I want to change direction to the right",
		"optionC": "Yes, because I want to go straight ahead",
		"Answer": "C",
		"Explanation": "For Explanation, please be a member or comment on our youtube channel."
	},
	{
		"ID": "506",
		"question": "Should putting your hands on the steering wheel correctly be a principle for safer driving?",
		"image": "https://raw.githubusercontent.com/sdriveportugal/web/refs/heads/main/SetPics/circulation-1/506.png",
		"optionA": "No, because having both hands on the wheel is only necessary when driving on the motorway",
		"optionB": "Yes, but only as long as the driver is not very experienced",
		"optionC": "Yes, always",
		"Answer": "C",
		"Explanation": "For Explanation, please be a member or comment on our youtube channel."
	},
	{
		"ID": "516",
		"question": "What should I do if I drop a load at the level crossing?",
		"image": "https://raw.githubusercontent.com/sdriveportugal/web/refs/heads/main/SetPics/circulation-1/516.png",
		"optionA": "I should leave the level crossing immediately, call the fire brigade and not move the load",
		"optionB": "I should continue travelling and warn the authorities",
		"optionC": "I must try to remove the load from the level crossing as quickly as possible",
		"Answer": "C",
		"Explanation": "For Explanation, please be a member or comment on our youtube channel."
	},
	{
		"ID": "520",
		"question": "Do you consider that this driver has his hands correctly placed on the steering wheel?",
		"image": "https://raw.githubusercontent.com/sdriveportugal/web/refs/heads/main/SetPics/circulation-1/520.png",
		"optionA": "No, because it's never necessary to put both hands on the wheel",
		"optionB": "Yes, although two-way traffic is only necessary when travelling at high speeds",
		"optionC": "Yes.",
		"Answer": "C",
		"Explanation": "For Explanation, please be a member or comment on our youtube channel."
	},
	{
		"ID": "522",
		"question": "Visibility shall be considered not sufficient, if the driver does not see the carriageway, across the entire width for at least the following:",
		"image": "https://raw.githubusercontent.com/sdriveportugal/web/refs/heads/main/SetPics/circulation-1/522.png",
		"optionA": "150 metres",
		"optionB": "50 metres",
		"optionC": "75 metres",
		"Answer": "B",
		"Explanation": "For Explanation, please be a member or comment on our youtube channel."
	},
	{
		"ID": "525",
		"question": "Should I continue to drive on this traffic lane?",
		"image": "https://raw.githubusercontent.com/sdriveportugal/web/refs/heads/main/SetPics/circulation-1/525.png",
		"optionA": "No.",
		"optionB": "Yes, if my intention is to change direction to the right",
		"optionC": "Yes, if my intention is to change direction to the left",
		"Answer": "B",
		"Explanation": "For Explanation, please be a member or comment on our youtube channel."
	},
	{
		"ID": "529",
		"question": "Can I use a mobile phone equipped with a headset while driving?",
		"image": "https://raw.githubusercontent.com/sdriveportugal/web/refs/heads/main/SetPics/circulation-1/529.png",
		"optionA": "No, unless the device has two earphones or a microphone with a loudspeaker system",
		"optionB": "No, unless the device has a headset and its use does not involve continuous handling",
		"optionC": "Yes, even if its use involves continuous handling",
		"Answer": "B",
		"Explanation": "For Explanation, please be a member or comment on our youtube channel."
	},
	{
		"ID": "531",
		"question": "In the event of a breakdown in my vehicle I can use this phone to:",
		"image": "https://raw.githubusercontent.com/sdriveportugal/web/refs/heads/main/SetPics/circulation-1/531.png",
		"optionA": "Call a taxi",
		"optionB": "Informing the relevant authorities",
		"optionC": "Call a garage..",
		"Answer": "B",
		"Explanation": "For Explanation, please be a member or comment on our youtube channel."
	}
]
